fastcoref/__init__.py
fastcoref/widgets/__init__.py
fastcoref/widgets/coreference_resolution.py
fastcoref/widgets/icons/category.svg
fastcoref/widgets/icons/mywidget.svg
orange_fastcoref_plugin-0.1.1.dist-info/licenses/LICENSE
orange_fastcoref_plugin-0.1.1.dist-info/METADATA
orange_fastcoref_plugin-0.1.1.dist-info/WHEEL
orange_fastcoref_plugin-0.1.1.dist-info/entry_points.txt
orange_fastcoref_plugin-0.1.1.dist-info/top_level.txt
orange_fastcoref_plugin-0.1.1.dist-info/RECORD
